loci_snyk/__init__.py
loci_snyk/main.py
loci_snyk/run.py
loci_snyk/utils.py
loci_snyk-0.1.0.dist-info/METADATA
loci_snyk-0.1.0.dist-info/WHEEL
loci_snyk-0.1.0.dist-info/entry_points.txt
loci_snyk-0.1.0.dist-info/top_level.txt
loci_snyk-0.1.0.dist-info/RECORD
