Metadata-Version: 2.1
Name: loci-snyk
Version: 0.1.0
Summary: The official Loci Notes Snyk results output processor.
Home-page: https://gitlab.com/loci-notes/loci-snyk
Author: TheTwitchy
Author-email: thetwitchy@thetwitchy.com
License: UNKNOWN
Platform: UNKNOWN
Requires-Dist: click
Requires-Dist: requests
Requires-Dist: rich
Requires-Dist: pendulum
